tableascii/__init__.py
tableascii/core.py
tableascii-0.1.0.dist-info/licenses/LICENSE
tableascii-0.1.0.dist-info/METADATA
tableascii-0.1.0.dist-info/WHEEL
tableascii-0.1.0.dist-info/top_level.txt
tableascii-0.1.0.dist-info/RECORD
