Metadata-Version: 2.4
Name: tableascii
Version: 0.1.0
Summary: A lightweight, simple Python library to create clean ASCII Table.
Home-page: https://github.com/Tari-dev/tableascii
Author: Tariq Muhammed
Project-URL: Source, https://github.com/Tari-dev/tableascii
Project-URL: Bug Tracker, https://github.com/Tari-dev/tableascii/issues
Classifier: Programming Language :: Python :: 3
Classifier: License :: OSI Approved :: MIT License
Requires-Python: >=3.6
License-File: LICENSE
Dynamic: author
Dynamic: classifier
Dynamic: description
Dynamic: description-content-type
Dynamic: home-page
Dynamic: license-file
Dynamic: project-url
Dynamic: requires-python
Dynamic: summary
